.appveyor.yml
.bumpversion.cfg
.cookiecutterrc
.coveragerc
.editorconfig
.pre-commit-config.yaml
.readthedocs.yml
.travis.yml
AUTHORS.rst
CHANGELOG.rst
CONTRIBUTING.rst
LICENSE
MANIFEST.in
README.rst
setup.cfg
setup.py
tox.ini
ci/bootstrap.py
ci/requirements.txt
ci/templates/.appveyor.yml
ci/templates/.travis.yml
src/publishextrator/__init__.py
src/publishextrator/__main__.py
src/publishextrator/cli.py
src/publishextrator/file1.py
src/publishextrator.egg-info/PKG-INFO
src/publishextrator.egg-info/SOURCES.txt
src/publishextrator.egg-info/dependency_links.txt
src/publishextrator.egg-info/entry_points.txt
src/publishextrator.egg-info/not-zip-safe
src/publishextrator.egg-info/requires.txt
src/publishextrator.egg-info/top_level.txt
tests/test_publishextrator.py