Metadata-Version: 2.1
Name: publishextrator
Version: 0.0.4
Summary: PublishNews extractor
Home-page: https://github.com/JonasBrother97/python-publishextrator
Author: joao gm
Author-email: joaogsmachado1@gmail.com
License: BSD-2-Clause
Project-URL: Documentation, https://python-publishextrator.readthedocs.io/
Project-URL: Changelog, https://python-publishextrator.readthedocs.io/en/latest/changelog.html
Project-URL: Issue Tracker, https://github.com/JonasBrother97/python-publishextrator/issues
Platform: UNKNOWN
Classifier: Development Status :: 5 - Production/Stable
Classifier: Intended Audience :: Developers
Classifier: License :: OSI Approved :: BSD License
Classifier: Operating System :: Unix
Classifier: Operating System :: POSIX
Classifier: Operating System :: Microsoft :: Windows
Classifier: Programming Language :: Python
Classifier: Programming Language :: Python :: 3
Classifier: Programming Language :: Python :: 3 :: Only
Classifier: Programming Language :: Python :: 3.6
Classifier: Programming Language :: Python :: 3.7
Classifier: Programming Language :: Python :: 3.8
Classifier: Programming Language :: Python :: 3.9
Classifier: Programming Language :: Python :: Implementation :: CPython
Classifier: Programming Language :: Python :: Implementation :: PyPy
Classifier: Topic :: Utilities
Requires-Python: >=3.6
License-File: LICENSE
License-File: AUTHORS.rst
